_amplpy_gurobi_swig.cpython-36m-darwin.so
amplpy_gurobi/.gitignore
amplpy_gurobi/__init__.py
amplpy_gurobi/patch.py
amplpy_gurobi/cpp/ampls/CMakeLists.txt
amplpy_gurobi/cpp/ampls/examples/addEntities.cpp
amplpy_gurobi/cpp/ampls/examples/benders.cpp
amplpy_gurobi/cpp/ampls/examples/callbacks.cpp
amplpy_gurobi/cpp/ampls/examples/cuttingStock.cpp
amplpy_gurobi/cpp/ampls/examples/errorDetection.cpp
amplpy_gurobi/cpp/ampls/examples/getInformation.cpp
amplpy_gurobi/cpp/ampls/examples/loadModel.cpp
amplpy_gurobi/cpp/ampls/examples/multipleModels.cpp
amplpy_gurobi/cpp/ampls/examples/multipleSolutions.cpp
amplpy_gurobi/cpp/ampls/examples/setOptions.cpp
amplpy_gurobi/cpp/ampls/examples/stoppingCriteria.cpp
amplpy_gurobi/cpp/ampls/examples/tsp.cpp
amplpy_gurobi/cpp/ampls/include/ampls/ampls.h
amplpy_gurobi/cpp/ampls/src/ampls.cpp
amplpy_gurobi/cpp/ampls/src/csvReader.cpp
amplpy_gurobi/cpp/ampls/src/csvReader.h
amplpy_gurobi/cpp/ampls/swig/ampls-common.i
amplpy_gurobi/cpp/ampls/test/addEntities-test.cpp
amplpy_gurobi/cpp/ampls/test/cuttingStock-test.cpp
amplpy_gurobi/cpp/ampls/test/errorDetection-test.cpp
amplpy_gurobi/cpp/ampls/test/getInformation-test.cpp
amplpy_gurobi/cpp/ampls/test/loadModel-test.cpp
amplpy_gurobi/cpp/ampls/test/multipleModels-test.cpp
amplpy_gurobi/cpp/ampls/test/multipleSolutions-test.cpp
amplpy_gurobi/cpp/ampls/test/setOptions-test.cpp
amplpy_gurobi/cpp/ampls/test/test-base.h
amplpy_gurobi/cpp/ampls/test/test-execute.h
amplpy_gurobi/cpp/ampls/test/tsp-test.cpp
amplpy_gurobi/cpp/gurobi/examples/getInformation.cpp
amplpy_gurobi/cpp/gurobi/examples/loadModel.cpp
amplpy_gurobi/cpp/gurobi/examples/simpleCuts.cpp
amplpy_gurobi/cpp/gurobi/include/gurobi_callback.h
amplpy_gurobi/cpp/gurobi/include/gurobi_interface.h
amplpy_gurobi/cpp/gurobi/src/gurobi_callback.cpp
amplpy_gurobi/cpp/gurobi/src/gurobi_interface.cpp
amplpy_gurobi/cpp/gurobi/swig/gurobi-common.i
amplpy_gurobi/cpp/gurobi/test/gurobi-test.cpp
amplpy_gurobi/libs/gurobi/include/.gitignore
amplpy_gurobi-0.2.2.dist-info/METADATA
amplpy_gurobi-0.2.2.dist-info/WHEEL
amplpy_gurobi-0.2.2.dist-info/top_level.txt
amplpy_gurobi-0.2.2.dist-info/RECORD
